{
  "id": "fd-editor-email-input",
  "editorUIElements": [
    {
      "type": "section",
      "htmlClass": "row",
      "items": [
        {
          "type": "section",
          "htmlClass": "col-sm-6",
          "items": [
            {
              "key": "key",
              "title": "Key",
              "description": "The dot notated model attribute",
              "placeholder": "e.g., email",
              "required": true,
              "feedback": true,
              "enableSuccessState": true,
              "enableErrorState": true,
              "pattern": "(^[A-Za-z_$][\\w$.]*[\\w$](?=$)$)|(^[A-Za-z_$]$)",
              "validationMessage": "Can only start with: 'a-zA-Z_$', can contain 'a-zA-Z0-9_$.', can only end with 'a-zA-Z0-9_$'"
            }
          ]
        },
        {
          "type": "section",
          "htmlClass": "col-sm-6",
          "items": [
            {
              "key": "uiElementProperties.title",
              "title": "Label",
              "description": "Label of this form control",
              "placeholder": "e.g., Email"
            }
          ]
        }
      ]
    },
    {
      "type": "section",
      "htmlClass": "row",
      "items": [
        {
          "type": "section",
          "htmlClass": "col-sm-6",
          "items": [
            {
              "key": "uiElementProperties.readonly",
              "title": "Read-only",
              "description": "Check if this field is read-only"
            }
          ]
        },
        {
          "type": "section",
          "htmlClass": "col-sm-6",
          "items": [
            {
              "key": "uiElementProperties.notitle",
              "title": "Hide Label",
              "description": "If checked, the title will be hidden"
            }
          ]
        }
      ]
    },
    {
      "type": "section",
      "htmlClass": "row",
      "items": [
        {
          "type": "section",
          "htmlClass": "col-sm-6",
          "items": [
            {
              "key": "uiElementProperties.description",
              "title": "Description",
              "description": "A description text like this. Support HTML except for the \"style\" attribute",
              "placeholder": ""
            }
          ]
        },
        {
          "type": "section",
          "htmlClass": "col-sm-6",
          "items": [
            {
              "key": "uiElementProperties.messageLocation",
              "title": "Description Location",
              "description": "'top' or 'bottom'"
            }
          ]
        }
      ]
    },
    {
      "type": "section",
      "htmlClass": "row",
      "items": [
        {
          "type": "section",
          "htmlClass": "col-sm-6",
          "items": [
            {
              "key": "uiElementProperties.placeholder",
              "title": "Placeholder",
              "description": "The light backgroud text shown when there is no content in this form control",
              "placeholder": "A placeholder value like this"
            }
          ]
        },
        {
          "type": "section",
          "htmlClass": "col-sm-6",
          "items": [
            {
              "key": "uiElementProperties.htmlClass",
              "title": "HTML Class",
              "description": "CSS Class(es) for this component",
              "placeholder": "e.g., bg-info"
            }
          ]
        }
      ]
    },
    {
      "type": "section",
      "htmlClass": "row",
      "items": [
        {
          "type": "section",
          "htmlClass": "col-sm-6",
          "items": [
            {
              "key": "uiElementProperties.labelHtmlClass",
              "title": "Label HTML Class",
              "description": "CSS Class(es) for the field label",
              "placeholder": "e.g., text-right"
            }
          ]
        },
        {
          "type": "section",
          "htmlClass": "col-sm-6",
          "items": [
            {
              "key": "uiElementProperties.fieldHtmlClass",
              "title": "Field HTML Class",
              "description": "CSS Class(es) for the field control",
              "placeholder": "e.g., text-left"
            }
          ]
        }
      ]
    },
    {
      "type": "section",
      "htmlClass": "row",
      "items": [
        {
          "type": "section",
          "htmlClass": "col-sm-6",
          "items": [
            {
              "key": "uiElementProperties.enableSuccessState",
              "title": "Enable Success State",
              "description": "Enable success state feedback"
            }
          ]
        },
        {
          "type": "section",
          "htmlClass": "col-sm-6",
          "items": [
            {
              "key": "uiElementProperties.enableErrorState",
              "title": "Enable Error State",
              "description": "Enable error state feedback"
            }
          ]
        }
      ]
    },
    {
      "type": "section",
      "htmlClass": "row",
      "items": [
        {
          "type": "section",
          "htmlClass": "col-sm-6",
          "items": [
            {
              "key": "uiElementProperties.feedback",
              "title": "Show Feedback",
              "description": "Switch on/off success and error feedback glyphicons"
            }
          ]
        },
        {
          "type": "section",
          "htmlClass": "col-sm-6",
          "items": [
            {
              "key": "uiElementProperties.feedbackOnRender",
              "title": "Show Feedback on Render",
              "description": "Switch on/off showing feedback immediately after form is renderred"
            }
          ]
        }
      ]
    },
    {
      "type": "section",
      "htmlClass": "row",
      "items": [
        {
          "type": "section",
          "htmlClass": "col-sm-6",
          "items": [
            {
              "key": "uiElementProperties.fieldAddonLeft",
              "title": "Left Field Addon",
              "description": "The field addon on the left",
              "placeholder": "e.g., $"
            }
          ]
        },
        {
          "type": "section",
          "htmlClass": "col-sm-6",
          "items": [
            {
              "key": "uiElementProperties.fieldAddonRight",
              "title": "Right Field Addon",
              "description": "The field addon on the right",
              "placeholder": "e.g., %"
            }
          ]
        }
      ]
    },
    {
      "type": "section",
      "htmlClass": "row",
      "items": [
        {
          "type": "section",
          "htmlClass": "col-sm-6",
          "items": [
            {
              "key": "schemaProperties.default",
              "title": "Default Value",
              "description": "Field default value"
            }
          ]
        },
        {
          "type": "section",
          "htmlClass": "col-sm-6",
          "items": [
            {
              "key": "uiElementProperties.required",
              "title": "Required",
              "description": "Check if this field is mandatory"
            }
          ]
        }
      ]
    }
  ],
  "editorSchema": {
    "type": "object",
    "properties": {
      "key": {
        "type": "string"
      },
      "uiElementProperties": {
        "type": "object",
        "properties": {
          "type": {
            "type": "string"
          },
          "title": {
            "type": "string"
          },
          "readonly": {
            "type": "boolean"
          },
          "notitle": {
            "type": "boolean"
          },
          "description": {
            "type": "string"
          },
          "messageLocation": {
            "type": "string",
            "enum": [
              "bottom",
              "top"
            ],
            "default": "bottom"
          },
          "placeholder": {
            "type": "string"
          },
          "htmlClass": {
            "type": "string"
          },
          "fieldHtmlClass": {
            "type": "string"
          },
          "labelHtmlClass": {
            "type": "string"
          },
          "enableSuccessState": {
            "type": "boolean"
          },
          "enableErrorState": {
            "type": "boolean"
          },
          "feedback": {
            "type": "boolean"
          },
          "feedbackOnRender": {
            "type": "boolean"
          },
          "fieldAddonLeft": {
            "type": "string"
          },
          "fieldAddonRight": {
            "type": "string"
          },
          "required": {
            "type": "boolean"
          },
          "format": {
            "type": "string"
          }
        }
      },
      "schemaProperties": {
        "type": "object",
        "properties": {
          "type": {
            "type": "string"
          },
          "default": {
            "type": "string"
          }
        }
      }
    }
  }
}
